Handnachweise/Beton.py
Handnachweise/__init__.py
Handnachweise-0.0.101.dist-info/METADATA
Handnachweise-0.0.101.dist-info/WHEEL
Handnachweise-0.0.101.dist-info/top_level.txt
Handnachweise-0.0.101.dist-info/RECORD
